messenger_gb_server-0.0.3.data/scripts/server_run
server/__init__.py
server/server.py
server/doc/__init__.py
server/doc/source/__init__.py
server/doc/source/conf.py
server/server/__init__.py
server/server/common/__init__.py
server/server/common/add_user.py
server/server/common/alerts.py
server/server/common/config_window.py
server/server/common/constants.py
server/server/common/decorators.py
server/server/common/functions.py
server/server/common/main_window.py
server/server/common/remove_user.py
server/server/common/server_class.py
server/server/common/sevrer_db.py
server/server/common/stat_window.py
server/server/logs/__init__.py
server/server/logs/config_server_log.py
messenger_gb_server-0.0.3.dist-info/METADATA
messenger_gb_server-0.0.3.dist-info/WHEEL
messenger_gb_server-0.0.3.dist-info/top_level.txt
messenger_gb_server-0.0.3.dist-info/RECORD
