Metadata-Version: 2.1
Name: messenger-gb-server
Version: 0.0.3
Summary: messenger_gb_server
Home-page: UNKNOWN
Author: Alexey Kh
Author-email: mraxe@bk.ru
License: UNKNOWN
Platform: UNKNOWN
Requires-Dist: PyQt5
Requires-Dist: sqlalchemy
Requires-Dist: pycryptodome
Requires-Dist: pycryptodomex
